AUTHOR.txt
README.txt
bootstrap.py
buildout.cfg
setup.py
src/z3c/__init__.py
src/z3c.schemadiff.egg-info/PKG-INFO
src/z3c.schemadiff.egg-info/SOURCES.txt
src/z3c.schemadiff.egg-info/dependency_links.txt
src/z3c.schemadiff.egg-info/namespace_packages.txt
src/z3c.schemadiff.egg-info/not-zip-safe
src/z3c.schemadiff.egg-info/requires.txt
src/z3c.schemadiff.egg-info/top_level.txt
src/z3c/difftool/README.txt
src/z3c/difftool/__init__.py
src/z3c/difftool/browser.py
src/z3c/difftool/configure.zcml
src/z3c/difftool/diff.pt
src/z3c/difftool/field.py
src/z3c/difftool/interfaces.py
src/z3c/difftool/schema.py
src/z3c/difftool/tests.py